COPYING
HACKING.rst
MANIFEST.in
Makefile
README.rst
juju-git-deploy
requirements.pip
setup.py
test-requirements.pip
juju_git_deploy.egg-info/PKG-INFO
juju_git_deploy.egg-info/SOURCES.txt
juju_git_deploy.egg-info/dependency_links.txt
juju_git_deploy.egg-info/not-zip-safe
juju_git_deploy.egg-info/requires.txt
juju_git_deploy.egg-info/top_level.txt
jujugd/__init__.py
jujugd/api.py
jujugd/app.py
jujugd/env.py
jujugd/manage.py
jujugd/utils.py
jujugd/tests/__init__.py
jujugd/tests/helpers.py
jujugd/tests/test_api.py
jujugd/tests/test_app.py
jujugd/tests/test_env.py
jujugd/tests/test_manage.py
jujugd/tests/test_utils.py