Metadata-Version: 1.1
Name: juju-git-deploy
Version: 0.1.1
Summary: Deploy Juju services from local charms hosted on Github.
Home-page: https://github.com/frankban/juju-git-deploy
Author: Francesco Banconi
Author-email: francesco.banconi@canonical.com
License: UNKNOWN
Keywords: juju git-deploy plugin github
Platform: UNKNOWN
Classifier: Development Status :: 5 - Production/Stable
Classifier: Environment :: Web Environment
Classifier: Intended Audience :: System Administrators
Classifier: License :: OSI Approved :: GNU Affero General Public License v3
Classifier: Operating System :: POSIX
Classifier: Programming Language :: Python :: 3
Classifier: Topic :: System :: Installation/Setup
